pakku/__init__.py
pakku/main.py
pakku-0.1.1.dist-info/METADATA
pakku-0.1.1.dist-info/WHEEL
pakku-0.1.1.dist-info/entry_points.txt
pakku-0.1.1.dist-info/top_level.txt
pakku-0.1.1.dist-info/RECORD
