Metadata-Version: 2.4
Name: pakku
Version: 0.1.1
Summary: A lightweight Feature Rich Python package manager with GUI.
Home-page: https://github.com/AlphaDarkmoon/pakku
Author: AlphaDarkmoon
Classifier: Programming Language :: Python :: 3
Classifier: Operating System :: OS Independent
Requires-Python: >=3.6
Requires-Dist: PyQt5
Requires-Dist: requests
Requires-Dist: psutil
Dynamic: author
Dynamic: classifier
Dynamic: description
Dynamic: description-content-type
Dynamic: home-page
Dynamic: requires-dist
Dynamic: requires-python
Dynamic: summary
